{
  "project_info": {
    "project_number": "436817852421",
    "firebase_url": "https://memoryroadappv2.firebaseio.com",
    "project_id": "memoryroadappv2",
    "storage_bucket": "memoryroadappv2.appspot.com"
  },
  "client": [
    {
      "client_info": {
        "mobilesdk_app_id": "1:436817852421:android:1fbf9431f3d1dce3cc446c",
        "android_client_info": {
          "package_name": "com.example.memoryroadapp"
        }
      },
      "oauth_client": [
        {
          "client_id": "436817852421-qmkkml1o35emg5a8n40m17afi2dsnig9.apps.googleusercontent.com",
          "client_type": 1,
          "android_info": {
            "package_name": "com.example.memoryroadapp",
            "certificate_hash": "13fb91addf67c1e653d45b005a87e152829d6068"
          }
        },
        {
          "client_id": "436817852421-je6urmvmasemuoicoi43ir1hobhqmb26.apps.googleusercontent.com",
          "client_type": 3
        }
      ],
      "api_key": [
        {
          "current_key": "AIzaSyDS0cNDOVKQMuGhXLR7xrMHdTcr0RuSsts"
        }
      ],
      "services": {
        "appinvite_service": {
          "other_platform_oauth_client": [
            {
              "client_id": "436817852421-je6urmvmasemuoicoi43ir1hobhqmb26.apps.googleusercontent.com",
              "client_type": 3
            }
          ]
        }
      }
    }
  ],
  "configuration_version": "1"
}